mkidgen3-1.0.0.dist-info/METADATA
mkidgen3-1.0.0.dist-info/WHEEL
mkidgen3-1.0.0.dist-info/entry_points.txt
mkidgen3-1.0.0.dist-info/licenses/LICENSE
mkidgen3/__init__.py
mkidgen3/config/HexRegisterValues_LMK04208_Default_ZCU111.txt
mkidgen3/config/LMK04828_256.0_MTS.txt
mkidgen3/config/LMK04828_500.0_MTS.txt
mkidgen3/config/LMK04828_512.0_MTS.txt
mkidgen3/config/LMK04828_512_dualloop.txt
mkidgen3/config/LMX2594_409.6_256FoscMTS.txt
mkidgen3/config/LMX2594_4096.0.txt
mkidgen3/config/LMX2594_500.0_MTS.txt
mkidgen3/config/LMX2594_512.0_MTS.txt
mkidgen3/config/ZCU111_LMK04208_10MHz_Ref_J109SMA.txt
mkidgen3/config/logging.yaml
mkidgen3/config/waveform_phase_pulse.npy
mkidgen3/daccomb.py
mkidgen3/drivers/__init__.py
mkidgen3/drivers/axififo.py
mkidgen3/drivers/axiswitch.py
mkidgen3/drivers/bintores.py
mkidgen3/drivers/capture.py
mkidgen3/drivers/dactable.py
mkidgen3/drivers/ddc.py
mkidgen3/drivers/ddssweep.py
mkidgen3/drivers/ifboard.py
mkidgen3/drivers/iqgen.py
mkidgen3/drivers/mcdma.py
mkidgen3/drivers/phasematch.py
mkidgen3/drivers/ppssync.py
mkidgen3/drivers/rfdc.py
mkidgen3/drivers/rfdcclock.py
mkidgen3/drivers/trigger.py
mkidgen3/equipment_drivers/anritsu.py
mkidgen3/equipment_drivers/ifboard.py
mkidgen3/fixedpoint.py
mkidgen3/funcs.py
mkidgen3/g3_paper.py
mkidgen3/gen2.py
mkidgen3/interrupts.py
mkidgen3/mkid_setup/interactive_setup.py
mkidgen3/mkid_setup/loop_locator.py
mkidgen3/mkid_setup/sweeps.py
mkidgen3/mkidpynq.py
mkidgen3/opfb.py
mkidgen3/overlay_helpers.py
mkidgen3/plotting.py
mkidgen3/power_sweep_helpers.py
mkidgen3/quirks.py
mkidgen3/registers.py
mkidgen3/rfsocmemory.py
mkidgen3/server/__init__.py
mkidgen3/server/aggregator.py
mkidgen3/server/captures.py
mkidgen3/server/feedline_client.py
mkidgen3/server/feedline_config.py
mkidgen3/server/feedline_server.py
mkidgen3/server/fpga_objects.py
mkidgen3/server/misc.py
mkidgen3/server/photontable.py
mkidgen3/server/pixelmap.py
mkidgen3/server/waveform.py
mkidgen3/system_parameters.py
mkidgen3/util.py
mkidgen3-1.0.0.dist-info/RECORD
