Metadata-Version: 2.1
Name: mkidgen3
Version: 1.0.0
Summary: Drivers and Client/Server control library for Mazin Labs 3rd generation MKID readout
Author: John I. Bailey, III, Jennifer Pearl Smith, Aled V. Cuda, Mazin Lab contributors
Maintainer: Jennifer Pearl Smith
Maintainer-Email: "Aled V. Cuda" <aled@ucsb.edu>
License:                     GNU GENERAL PUBLIC LICENSE
Requires-Python: >=3.10
Requires-Dist: numpy>=1.21
Requires-Dist: scipy>=1.8.0
Requires-Dist: pyserial>=3.5
Requires-Dist: pyyaml>=5.4.1
Provides-Extra: board
Requires-Dist: pynq>=3.0.1; extra == "board"
Requires-Dist: fpbinary==1.5.8; extra == "board"
Requires-Dist: xrfdc==2.0; extra == "board"
Requires-Dist: xrfclk==2.0; extra == "board"
Provides-Extra: anritsu
Requires-Dist: requests>=2.25.0; extra == "anritsu"
Provides-Extra: sccommon
Requires-Dist: pyzmq>=23.2.0; extra == "sccommon"
Requires-Dist: blosc2>=2.2.0; extra == "sccommon"
Requires-Dist: tqdm>=4.64.0; extra == "sccommon"
Provides-Extra: server
Requires-Dist: psutil>=5.9.0; extra == "server"
Requires-Dist: mkidgen3[board,sccommon]; extra == "server"
Provides-Extra: client
Requires-Dist: h5py>=3.10.0; extra == "client"
Requires-Dist: hdf5plugin>=4.4.0; extra == "client"
Requires-Dist: npy-append-array==0.9.16; extra == "client"
Requires-Dist: mkidgen3[sccommon]; extra == "client"
Provides-Extra: plotting
Requires-Dist: matplotlib>=3.5.1; extra == "plotting"
